CHANGES.rst
MANIFEST.in
README.rst
setup.py
Products/__init__.py
Products.AddRemoveWidget.egg-info/PKG-INFO
Products.AddRemoveWidget.egg-info/SOURCES.txt
Products.AddRemoveWidget.egg-info/dependency_links.txt
Products.AddRemoveWidget.egg-info/entry_points.txt
Products.AddRemoveWidget.egg-info/namespace_packages.txt
Products.AddRemoveWidget.egg-info/not-zip-safe
Products.AddRemoveWidget.egg-info/requires.txt
Products.AddRemoveWidget.egg-info/top_level.txt
Products/AddRemoveWidget/AddRemoveWidget.py
Products/AddRemoveWidget/ComboBoxWidget.py
Products/AddRemoveWidget/__init__.py
Products/AddRemoveWidget/configure.zcml
Products/AddRemoveWidget/rebuild_po.sh
Products/AddRemoveWidget/locales/AddRemoveWidget.pot
Products/AddRemoveWidget/locales/cs/LC_MESSAGES/AddRemoveWidget.po
Products/AddRemoveWidget/locales/da/LC_MESSAGES/AddRemoveWidget.po
Products/AddRemoveWidget/locales/de/LC_MESSAGES/AddRemoveWidget.po
Products/AddRemoveWidget/locales/en/LC_MESSAGES/AddRemoveWidget.po
Products/AddRemoveWidget/locales/es/LC_MESSAGES/AddRemoveWidget.po
Products/AddRemoveWidget/locales/fr/LC_MESSAGES/AddRemoveWidget.po
Products/AddRemoveWidget/locales/nl/LC_MESSAGES/AddRemoveWidget.po
Products/AddRemoveWidget/locales/zh_TW/LC_MESSAGES/AddRemoveWidget.po
Products/AddRemoveWidget/profiles/default/metadata.xml
Products/AddRemoveWidget/profiles/default/skins.xml
Products/AddRemoveWidget/skins/AddRemoveWidget/widget_addremove.js
Products/AddRemoveWidget/skins/AddRemoveWidget/widget_addremove.pt
Products/AddRemoveWidget/skins/AddRemoveWidget/widget_addremove_vars.js.dtml
Products/AddRemoveWidget/skins/AddRemoveWidget/widget_combobox.pt
docs/LICENSE.LGPL
docs/LICENSE.txt