Metadata-Version: 1.1
Name: Products.AddRemoveWidget
Version: 1.5.2
Summary: AddRemoveWidget + ComboBoxWidget for Plone
Home-page: http://plone.org/products/addremovewidget
Author: Martin Aspeli
Author-email: optilude@gmx.net
License: LGPL
Keywords: Plone Archetypes Products AddRemoveWidget ComboBoxWidget
Platform: UNKNOWN
Classifier: Programming Language :: Python
Classifier: Programming Language :: Python :: 2.4
Classifier: Programming Language :: Python :: 2.6
Classifier: Programming Language :: Python :: 2.7
Classifier: Topic :: Software Development :: Libraries :: Python Modules
Classifier: Framework :: Plone
Classifier: Framework :: Plone :: 3.3
Classifier: Framework :: Plone :: 4.0
Classifier: Framework :: Plone :: 4.1
Classifier: Framework :: Plone :: 4.2
Classifier: Framework :: Plone :: 4.3
Classifier: Framework :: Zope2
